py_misinfo_exposure/__init__.py
py_misinfo_exposure/py_misinfo_exposure.py
py_misinfo_exposure/data/falsity_scores.csv
py_misinfo_exposure-1.1.dist-info/LICENSE
py_misinfo_exposure-1.1.dist-info/METADATA
py_misinfo_exposure-1.1.dist-info/WHEEL
py_misinfo_exposure-1.1.dist-info/top_level.txt
py_misinfo_exposure-1.1.dist-info/RECORD
