Metadata-Version: 2.1
Name: py-misinfo-exposure
Version: 1.1
Summary: Calculate misinformation-exposure scores for users based on the falsity scores of public figures they follow on Twitter.
Home-page: https://github.com/mr-devs/py_misinfo_exposure
Author: Matthew DeVerna
Author-email: mdeverna@iu.edu
License: Creative Commons
Download-URL: https://pypi.org/project/py_misinfo_exposure/
Project-URL: Documentation, https://github.com/mr-devs/py_misinfo_exposure
Project-URL: Issue Tracker, https://github.com/mr-devs/py_misinfo_exposure/issues
Project-URL: Source Code, https://github.com/mr-devs/py_misinfo_exposure
Platform: UNKNOWN
Requires-Python: >=3.7
License-File: LICENSE
Requires-Dist: tweepy (>=4.4.0)
Requires-Dist: pandas (>=1.2.4)
